{"id":346,"date":"2016-12-08T21:14:00","date_gmt":"2016-12-08T21:14:00","guid":{"rendered":"http://192.168.33.33/?post_type=stores&#038;p=346"},"modified":"2019-02-12T22:28:11","modified_gmt":"2019-02-12T22:28:11","slug":"b-test-store-8","status":"publish","type":"stores","link":"https://halcyon.dev.v3.imaginuitycenters.com/stores/b-test-store-8/","title":{"rendered":"B Test Store 8"},"template":"","imag_taxonomy_store_category":[62,41],"acf":{"logo_monochrome":"https://halcyon.dev.v3.imaginuitycenters.com/wp-content/uploads/sites/31/2016/10/aeropostale-logo-grey.jpg","featured_image":"https://halcyon.dev.v3.imaginuitycenters.com/wp-content/uploads/sites/31/2016/12/halcyon-tenant.png","store_copy":"<p>Lorem ipsum dolor sit amet, consectetur adipiscing elit. Sed vulputate rutrum mi, sagittis fringilla magna porttitor et. Quisque vitae purus.</p>\n","phone_number":"","restaurant_menu":false,"featured_video":"","standard_hours":[{"special_instructions":"","monday_closed":false,"monday_open":"","monday_close":"","tuesday_closed":false,"tuesday_open":"","tuesday_close":"","wednesday_closed":false,"wednesday_open":"","wednesday_close":"","thursday_closed":false,"thursday_open":"","thursday_close":"","friday_closed":false,"friday_open":"","friday_close":"","saturday_closed":false,"saturday_open":"","saturday_close":"","sunday_closed":false,"sunday_open":"","sunday_close":""}],"alternate_hours":false,"website":"","facebook":"","twitter":"","instagram":"","custom_hours":false,"flags":"","global_store_selector":{"selected_posts":[{"ID":1230,"post_author":"1","post_date":"2015-04-19 15:55:14","post_date_gmt":"2015-04-19 15:55:14","post_content":"Slip into a pair of Aerosoles and watch what happens. There is more spring in your step, more color in your life, simply stated more comfort. With more than 20 years of experience creating shoes we are passionate about our product and our core values remain the same…comfort, style, quality and value.","post_title":"Aerosoles","post_excerpt":"","post_status":"publish","comment_status":"closed","ping_status":"closed","post_password":"","post_name":"aerosoles","to_ping":"","pinged":"","post_modified":"2017-04-24 20:48:16","post_modified_gmt":"2017-04-24 20:48:16","post_content_filtered":"","post_parent":0,"guid":"http://centers3.imag-dev.com/global_stores/aerosoles/","menu_order":0,"post_type":"global_stores","post_mime_type":"","comment_count":"0","filter":"raw"}],"site_id":1},"store_type":"restaurant","custom_flag":false,"pinterest":"","hero_image_mobile":false,"hero_image_desktop":false,"logo":false,"subheading":"","street_address":"","nearby":"","convenient_parking":""},"yoast_meta":{"yoast_wpseo_title":"B Test Store 8 - Halcyon","yoast_wpseo_metadesc":"","yoast_wpseo_canonical":"https://halcyon.dev.v3.imaginuitycenters.com/stores/b-test-store-8/"},"_links":{"self":[{"href":"https://halcyon.dev.v3.imaginuitycenters.com/wp-json/wp/v2/stores/346"}],"collection":[{"href":"https://halcyon.dev.v3.imaginuitycenters.com/wp-json/wp/v2/stores"}],"about":[{"href":"https://halcyon.dev.v3.imaginuitycenters.com/wp-json/wp/v2/types/stores"}],"wp:attachment":[{"href":"https://halcyon.dev.v3.imaginuitycenters.com/wp-json/wp/v2/media?parent=346"}],"wp:term":[{"taxonomy":"imag_taxonomy_store_category","embeddable":true,"href":"https://halcyon.dev.v3.imaginuitycenters.com/wp-json/wp/v2/imag_taxonomy_store_category?post=346"}],"curies":[{"name":"wp","href":"https://api.w.org/{rel}","templated":true}]}}